{
  "component": {
    "buildings": {
      "form": {
        "apartment": {
          "apartment": "Apartment",
          "community": "House"
        },
        "floor": {
          "apartment": "Floor",
          "community": "Street"
        },
        "leave": {
          "label": "Leave",
          "message": "Are you sure you want to leave this building?",
          "no": "No",
          "title": "Are you sure?",
          "yes": "Yes"
        },
        "submit": "Save",
        "title": "Edit"
      },
      "picker": {
        "title": "Pick building"
      },
      "residency": {
        "code": {
          "close": "Close",
          "message": "Share this QR code with a neighbor and they can join {building}."
        }
      }
    },
    "chat": {
      "reply": {
        "placeholder": "Say something nice"
      }
    },
    "comments": {
      "form": {
        "placeholder": "Say something nice"
      }
    },
    "common": {
      "imageUploader": {
        "label": "Images"
      }
    },
    "notifications": {
      "card": {
        "comment": "<medium>{user}</medium> commented on your <medium>{type}</medium>."
      }
    },
    "posts": {
      "card": {
        "type": {
          "ad": "Ad",
          "event": "Event",
          "item": "Item",
          "post": "Post"
        }
      }
    }
  },
  "screen": {
    "account": {
      "buildings": {
        "title": "Manage buildings"
      },
      "menu": {
        "account": {
          "buildings": "Manage buildings",
          "profile": "Update profile",
          "title": "Account"
        },
        "security": {
          "exit": "Sign out",
          "title": "Security"
        }
      },
      "profile": {
        "form": {
          "bio": {
            "label": "About"
          },
          "name": {
            "error": "Name is required",
            "label": "Name"
          },
          "submit": "Save",
          "success": "Profile updated!"
        },
        "title": "Update profile"
      },
      "title": "Account"
    },
    "auth": {
      "signIn": {
        "form": {
          "email": {
            "error": "Email is required",
            "label": "Email",
            "placeholder": "me@example.com"
          },
          "password": {
            "error": "Password must be 6 characters or longer",
            "label": "Password",
            "placeholder": "P@s$w0rd"
          },
          "submit": "Sign in"
        },
        "title": "Sign in"
      },
      "signUp": {
        "form": {
          "email": {
            "error": "Email is required",
            "label": "Email",
            "placeholder": "me@example.com"
          },
          "name": {
            "error": "Name is required",
            "label": "Name",
            "placeholder": "Michael Scott"
          },
          "password": {
            "error": "Password must be 6 characters or longer",
            "label": "Password",
            "placeholder": "P@s$w0rd"
          },
          "submit": "Sign up"
        },
        "title": "Sign up"
      }
    },
    "chat": {
      "empty": "Nothing here",
      "loading": "Loading",
      "title": "Chat"
    },
    "home": {
      "empty": {
        "message": "Nobody's posted anything in your building. Be the first one?",
        "title": "Nothing here"
      },
      "title": "Home"
    },
    "landing": {
      "signIn": "Sign in",
      "signUp": "Sign up",
      "title": "<primary>Near</primary><accent>buds</accent>"
    },
    "notifications": {
      "empty": "Nothing here",
      "markRead": "Mark all as read",
      "title": "Notifications"
    },
    "onboarding": {
      "message": "Nearbuds is an invite only app. Have a neighbor share their QR code so you can join the building.",
      "notFound": "We couldn't find the building. Are you sure you scanned the right QR code?",
      "scan": "Scan a building QR code to join.",
      "success": "Welcome! Redirecting now.",
      "title": "Onboarding"
    },
    "posts": {
      "new": {
        "form": {
          "body": {
            "error": "Must be 10 characters or longer",
            "placeholder": {
              "event": "Describe your event",
              "item": "Describe your item",
              "post": "Say something nice"
            }
          },
          "currency": {
            "error": "Currency is required",
            "label": "Price currency",
            "placeholder": "Pick a currency"
          },
          "date": {
            "error": "Date is required",
            "label": "Date & time",
            "placeholder": "Pick a date and time"
          },
          "event": {
            "error": "Name is required",
            "label": "Event name",
            "placeholder": "House of the Dragon viewing party"
          },
          "price": {
            "error": "Price must be higher than 0",
            "label": "Price",
            "placeholder": "625"
          },
          "product": {
            "error": "Name is required",
            "label": "Product name",
            "placeholder": "iPhone 15 Pro"
          },
          "quantity": {
            "error": "Quantity must be higher than 0",
            "label": "Quantity",
            "placeholder": "2"
          },
          "submit": "Create",
          "type": {
            "event": "Event",
            "item": "Item",
            "label": "Type",
            "placeholder": "Type",
            "post": "Post"
          }
        },
        "title": {
          "event": "New event",
          "item": "New item",
          "post": "New post"
        }
      },
      "post": {
        "comments": {
          "empty": "Nothing here",
          "title": "Comments ({count, number})"
        },
        "title": {
          "ad": "Ad",
          "event": "Event",
          "item": "Item",
          "loading": "Loading",
          "post": "Post"
        }
      }
    },
    "search": {
      "empty": {
        "title": {
          "input": "Start typing to find stuff",
          "items": "Nothing found"
        }
      },
      "placeholder": "Search",
      "title": "Search"
    },
    "user": {
      "title": "Profile"
    }
  }
}
